odoo/addons/sale_order_requested_delivery/README.rst
odoo/addons/sale_order_requested_delivery/__init__.py
odoo/addons/sale_order_requested_delivery/__manifest__.py
odoo/addons/sale_order_requested_delivery/i18n/it.po
odoo/addons/sale_order_requested_delivery/i18n/sale_order_requested_delivery.pot
odoo/addons/sale_order_requested_delivery/models/__init__.py
odoo/addons/sale_order_requested_delivery/models/sale_order.py
odoo/addons/sale_order_requested_delivery/models/sale_order_line.py
odoo/addons/sale_order_requested_delivery/readme/CONTRIBUTORS.md
odoo/addons/sale_order_requested_delivery/readme/DESCRIPTION.md
odoo/addons/sale_order_requested_delivery/static/description/icon.png
odoo/addons/sale_order_requested_delivery/static/description/index.html
odoo/addons/sale_order_requested_delivery/tests/__init__.py
odoo/addons/sale_order_requested_delivery/tests/test_sale_order.py
odoo/addons/sale_order_requested_delivery/tests/test_sale_order_line.py
odoo/addons/sale_order_requested_delivery/views/sale_order.xml
odoo_addon_sale_order_requested_delivery-18.0.1.0.0.7.dist-info/METADATA
odoo_addon_sale_order_requested_delivery-18.0.1.0.0.7.dist-info/WHEEL
odoo_addon_sale_order_requested_delivery-18.0.1.0.0.7.dist-info/top_level.txt
odoo_addon_sale_order_requested_delivery-18.0.1.0.0.7.dist-info/RECORD
