Metadata-Version: 2.1
Name: odoo-addon-sale_order_requested_delivery
Version: 18.0.1.0.0.7
Requires-Python: >=3.10
Requires-Dist: odoo==18.0.*
Summary: This module adds two new fields `requested_delivery_period_start` and `requested_delivery_period_end` to both the `sale.order` and `sale.order.line` models.
Home-page: https://github.com/OCA/sale-workflow
License: AGPL-3
Author: Camptocamp, Odoo Community Association (OCA)
Author-email: support@odoo-community.org
Classifier: Programming Language :: Python
Classifier: Framework :: Odoo
Classifier: Framework :: Odoo :: 18.0
Classifier: License :: OSI Approved :: GNU Affero General Public License v3
